README.rst
setup.py
py_cryptocoin/__init__.py
py_cryptocoin/cryptocoin.py
py_cryptocoin.egg-info/PKG-INFO
py_cryptocoin.egg-info/SOURCES.txt
py_cryptocoin.egg-info/dependency_links.txt
py_cryptocoin.egg-info/not-zip-safe
py_cryptocoin.egg-info/top_level.txt