Metadata-Version: 1.1
Name: py-cryptocoin
Version: 1.0
Summary: Python3 CryptoCoin data parser
Home-page: https://bitbucket.org/tvdsluijs/py_cryptocoin
Author: Theodorus van der Sluijs
Author-email: theo@vandersluijs.nl
License: CC BY-NC-SA 4.0
Keywords: trains transport train dutch ns
Platform: UNKNOWN
Classifier: Programming Language :: Python :: 3
Classifier: Programming Language :: Python :: 3.3
Classifier: Programming Language :: Python :: 3.4
Classifier: Programming Language :: Python :: 3.5
